libtest001/Backwardcompatibility.py
libtest001/__init__.py
libtest001/__pycache__/good.dll
libtest001-0.0.0.dist-info/METADATA
libtest001-0.0.0.dist-info/WHEEL
libtest001-0.0.0.dist-info/top_level.txt
libtest001-0.0.0.dist-info/RECORD
