Metadata-Version: 2.1
Name: libtest001
Version: 0.0.0
Summary: Short description when they search in pip
Author: artitw
Author-email: XXXXXXXXX@gmail.com
Requires-Dist: requests
